textual_chat/__init__.py
textual_chat/agent_manager.py
textual_chat/chat.py
textual_chat/events.py
textual_chat/llm_adapter_acp.py
textual_chat/llm_adapter_litellm.py
textual_chat/py.typed
textual_chat/session_storage.py
textual_chat/slash_command.py
textual_chat/tools/__init__.py
textual_chat/tools/datatable.py
textual_chat/tools/introspection.py
textual_chat/utils/__init__.py
textual_chat/utils/models.py
textual_chat/widgets/__init__.py
textual_chat/widgets/agent_select.py
textual_chat/widgets/chat_input.py
textual_chat/widgets/message.py
textual_chat/widgets/model_select.py
textual_chat/widgets/permission_prompt.py
textual_chat/widgets/plan_pane.py
textual_chat/widgets/session_prompt.py
textual_chat/widgets/slash_command_autocomplete.py
textual_chat-0.1.4.dist-info/METADATA
textual_chat-0.1.4.dist-info/WHEEL
textual_chat-0.1.4.dist-info/RECORD
