Metadata-Version: 2.4
Name: textual-chat
Version: 0.1.4
Summary: LLM chat for humans. AI in your Textual app in a few lines.
License-Expression: MIT
Keywords: ai,chat,llm,textual,tui
Requires-Python: >=3.10
Requires-Dist: agent-client-protocol>=0.7.0
Requires-Dist: httpx>=0.27.0
Requires-Dist: litellm>=1.0.0
Requires-Dist: textual-autocomplete>=3.0.0
Requires-Dist: textual-golden
Requires-Dist: textual>=0.85.0
Provides-Extra: acp
Requires-Dist: agent-client-protocol>=0.6.0; extra == 'acp'
Provides-Extra: dev
Requires-Dist: fastmcp>=2.0.0; extra == 'dev'
Requires-Dist: pytest-asyncio>=0.24.0; extra == 'dev'
Requires-Dist: pytest>=8.0.0; extra == 'dev'
Requires-Dist: ruff>=0.8.0; extra == 'dev'
Provides-Extra: mcp
Requires-Dist: fastmcp>=2.0.0; extra == 'mcp'
